measure_text_entry_performance/__init__.py
measure_text_entry_performance/main.py
measure_text_entry_performance-0.2.4.dist-info/METADATA
measure_text_entry_performance-0.2.4.dist-info/WHEEL
measure_text_entry_performance-0.2.4.dist-info/RECORD
