Metadata-Version: 2.1
Name: measure_text_entry_performance
Version: 0.2.4
Summary: library to measure text entry performance
Home-page: https://github.com/2ndr9/measure_text_entry_performance
Author: 2ndr9
Requires-Python: >=3.9,<4.0
Classifier: Programming Language :: Python :: 3
Classifier: Programming Language :: Python :: 3.9
Classifier: Programming Language :: Python :: 3.10
Classifier: Programming Language :: Python :: 3.11
Project-URL: Repository, https://github.com/2ndr9/measure_text_entry_performance
